LICENSE
MANIFEST.in
README.md
setup.cfg
setup.py
cidrtrie/__init__.py
cidrtrie.egg-info/PKG-INFO
cidrtrie.egg-info/SOURCES.txt
cidrtrie.egg-info/dependency_links.txt
cidrtrie.egg-info/pbr.json
cidrtrie.egg-info/top_level.txt