Metadata-Version: 1.1
Name: cidrtrie
Version: 0.1
Summary: Prefix Tree (trie) for manipulating CIDR sets
Home-page: https://github.com/uber/cidrtrie
Author: James Brown
Author-email: jbrown@uber.com
License: MIT
Platform: UNKNOWN
Classifier: Development Status :: 4 - Beta
Classifier: Environment :: Web Environment
Classifier: Programming Language :: Python
Classifier: Programming Language :: Python :: 2.7
Classifier: Programming Language :: Python :: 3.2
Classifier: Programming Language :: Python :: 3.3
Classifier: Programming Language :: Python :: 3.4
Classifier: Intended Audience :: Developers
Classifier: Operating System :: OS Independent
Classifier: License :: OSI Approved :: MIT License
